erdio/__init__.py
erdio/__main__.py
erdio/cli.py
erdio/drawio.py
erdio/main.py
erdio/styles.py
erdio-0.0.3.dist-info/LICENSE
erdio-0.0.3.dist-info/METADATA
erdio-0.0.3.dist-info/WHEEL
erdio-0.0.3.dist-info/entry_points.txt
erdio-0.0.3.dist-info/top_level.txt
erdio-0.0.3.dist-info/RECORD
