Metadata-Version: 2.1
Name: erdio
Version: 0.0.3
Summary: CLI tool to convert DBML code to editable Draw.io diagram
Author-email: woodocat <woodocat@gmail.com>
Project-URL: Homepage, https://github.com/woodocat/erdio
Project-URL: Bug Tracker, https://github.com/woodocat/erdio/issues
Classifier: Programming Language :: Python :: 3
Classifier: License :: OSI Approved :: Apache Software License
Classifier: Operating System :: OS Independent
Requires-Python: >=3.8
License-File: LICENSE
Requires-Dist: click >=8.1.3
Requires-Dist: pydbml >=1.0.9
